odoo/addons/event_phone/README.rst
odoo/addons/event_phone/__init__.py
odoo/addons/event_phone/__manifest__.py
odoo/addons/event_phone/i18n/es.po
odoo/addons/event_phone/i18n/event_phone.pot
odoo/addons/event_phone/i18n/it.po
odoo/addons/event_phone/i18n/tr.po
odoo/addons/event_phone/models/__init__.py
odoo/addons/event_phone/models/event_registration.py
odoo/addons/event_phone/readme/CONTRIBUTORS.rst
odoo/addons/event_phone/readme/DESCRIPTION.rst
odoo/addons/event_phone/security/ir.model.access.csv
odoo/addons/event_phone/static/description/icon.png
odoo/addons/event_phone/static/description/index.html
odoo/addons/event_phone/tests/__init__.py
odoo/addons/event_phone/tests/test_phone.py
odoo/addons/event_phone/views/hr_registration.xml
odoo14_addon_event_phone-14.0.1.0.1.dev11.dist-info/METADATA
odoo14_addon_event_phone-14.0.1.0.1.dev11.dist-info/WHEEL
odoo14_addon_event_phone-14.0.1.0.1.dev11.dist-info/top_level.txt
odoo14_addon_event_phone-14.0.1.0.1.dev11.dist-info/RECORD
